{
  "usuarios": [],
  "aluno": {
    "nome": "Heberth Augusto",
    "bio": "Estudante de ANÁLISE E DESENVOLVIMENTO DE SISTEMAS.",
    "foto": "images/202442474.png",
    "redesSociais": [
      {
        "nome": "LinkedIn",
        "url": "#"
      },
      {
        "nome": "GitHub",
        "url": "https://github.com/Heeberth"
      },
      {
        "nome": "Instagram",
        "url": "https://www.instagram.com/heberth_sousa/"
      }
    ]
  },
  "favoritos": [
    {
      "id": "cf43",
      "filmeId": 950387,
      "title": "Um Filme Minecraft",
      "release_date": "2025-03-31",
      "overview": "Quatro desajustados enfrentam problemas comuns do dia a dia quando, de repente, são sugados por um portal misterioso para o Overworld: uma terra fascinante e cúbica, movida pela imaginação. Para voltarem para casa, eles precisarão dominar esse novo mundo enquanto embarcam em uma jornada mágica ao lado de um crafter experiente e inesperado: Steve.",
      "poster_path": "/4VtkIaj76TpQNfhDHXQDdT9uBN5.jpg"
    }
  ]
}